h5image/__init__.py
h5image/h5create.py
h5image/h5image.py
h5image-0.4.1.dist-info/METADATA
h5image-0.4.1.dist-info/WHEEL
h5image-0.4.1.dist-info/entry_points.txt
h5image-0.4.1.dist-info/top_level.txt
h5image-0.4.1.dist-info/RECORD
