Metadata-Version: 2.1
Name: h5image
Version: 0.4.1
Summary: Load and save images to HDF5 files
Author-email: Rob Kooper <kooper@illinois.edu>
Maintainer-email: Rob Kooper <kooper@illinois.edu>
Project-URL: Homepage, https://git.ncsa.illinois.edu/criticalmaas/h5image
Project-URL: Issues, https://git.ncsa.illinois.edu/criticalmaas/h5image/-/issues
Keywords: hdf5,image,map
Classifier: Programming Language :: Python :: 3
Classifier: License :: OSI Approved :: Mozilla Public License 2.0 (MPL 2.0)
Classifier: Operating System :: OS Independent
Requires-Python: >=3.6
Requires-Dist: affine
Requires-Dist: h5py
Requires-Dist: numpy
Requires-Dist: rasterio
Provides-Extra: dev
Requires-Dist: matplotlib ; extra == 'dev'
